<?xml version="1.0" encoding="UTF-8"?>
<!DOCTYPE hibernate-mapping PUBLIC 
    "-//Hibernate/Hibernate Mapping DTD 3.0//EN"
    "http://www.hibernate.org/dtd/hibernate-mapping-3.0.dtd">
<hibernate-mapping>
<class name="employeePackage.Employee" table="EMPLOYEE">
<id name="id" type="integer">
	<column name="ID"></column>
	<generator class="assigned"></generator>
</id>

<property name="name" column="ENAME" type="string"></property>
<property name="mobile" column="MOBILE" type="long"></property>
<property name="email" column="EMAIL" type="string"></property>
</class>



</hibernate-mapping>
